[
  {
    "id": 1,
    "title": "The Alchemist",
    "author": "Paulo Coelho",
    "year": 1988,
    "genre": "Adventure"
  },
  {
    "id": 2,
    "title": "To Kill a Mockingbird",
    "author": "Harper Lee",
    "year": 1960,
    "genre": "Fiction"
  },
  {
    "id": 3,
    "title": "1984",
    "author": "George Orwell",
    "year": 1949,
    "genre": "Dystopian"
  },
  {
    "id": 4,
    "title": "Pride and Prejudice",
    "author": "Jane Austen",
    "year": 1813,
    "genre": "Romance"
  },
  {
    "id": 5,
    "title": "The Great Gatsby",
    "author": "F. Scott Fitzgerald",
    "year": 1925,
    "genre": "Fiction"
  },
  {
    "id": 6,
    "title": "Moby Dick",
    "author": "Herman Melville",
    "year": 1851,
    "genre": "Adventure"
  },
  {
    "id": 7,
    "title": "The Catcher in the Rye",
    "author": "J.D. Salinger",
    "year": 1951,
    "genre": "Fiction"
  },
  {
    "id": 8,
    "title": "The Hobbit",
    "author": "J.R.R. Tolkien",
    "year": 1937,
    "genre": "Fantasy"
  },
  {
    "id": 9,
    "title": "Brave New World",
    "author": "Aldous Huxley",
    "year": 1932,
    "genre": "Dystopian"
  },
  {
    "id": 10,
    "title": "The Diary of a Young Girl",
    "author": "Anne Frank",
    "year": 1947,
    "genre": "Biography"
  }
]